sample/__init__.py
sample/__main__.py
sample/args.py
sample/csv.py
sample/dictionary.py
sample/epub.py
sample/main.py
sample/ocr.py
sample/pdf.py
sample/tokenizer.py
japanese_vocabulary_extractor-1.4.4.dist-info/LICENSE
japanese_vocabulary_extractor-1.4.4.dist-info/METADATA
japanese_vocabulary_extractor-1.4.4.dist-info/WHEEL
japanese_vocabulary_extractor-1.4.4.dist-info/entry_points.txt
japanese_vocabulary_extractor-1.4.4.dist-info/top_level.txt
japanese_vocabulary_extractor-1.4.4.dist-info/RECORD
