Metadata-Version: 2.1
Name: japanese-vocabulary-extractor
Version: 1.4.4
Summary: A utility to extract vocabulary lists from manga.
Home-page: https://github.com/Fluttrr/japanese-vocabulary-extractor
Author: Fluttrr
Author-email: ySZ39@proton.me
License: GLPv3
Classifier: Development Status :: 3 - Alpha
Classifier: Intended Audience :: Developers
Classifier: License :: OSI Approved :: GNU General Public License v3 (GPLv3)
Classifier: Programming Language :: Python :: 3
Classifier: Programming Language :: Python :: 3.7
Classifier: Programming Language :: Python :: 3.8
Classifier: Programming Language :: Python :: 3.9
Classifier: Programming Language :: Python :: 3.10
Requires-Python: >=3.7
License-File: LICENSE
Requires-Dist: regex
Requires-Dist: mokuro
Requires-Dist: mecab-python3
Requires-Dist: unidic-lite
Requires-Dist: pypdf
Requires-Dist: ebooklib
Requires-Dist: tqdm
Requires-Dist: jamdict
Requires-Dist: jamdict-data-fix
Requires-Dist: colorlog
